Workbook

Sheet Drivers
A1: CBG Techno-Economic Model — DRIVERS (yellow = editable)
A2: Single source of truth. Edit yellow cells; LiveModel recomputes. See sources/citations.md for tiers.
A4: # | B4: Driver | C4: Value | D4: Unit | E4: Tier | F4: Note
A5: D6 | B5: plf | C5: 0.5 | D5: frac | E5: T2 | F5: realized PLF yr2-3; silent killer
A6: D6 | B6: yr1_plf_ramp | C6: 0.35 | D6: frac | E6: INF | F6: year-1 ramp
A7: - | B7: operating_basis_days | C7: 365 | D7: days | E7: - | F7: PLF embeds downtime; 365×PLF
A8: D3 | B8: weighted_yield | C8: 27.5 | D8: kgCBG/t | E8: INF | F8: blend yield (dung 15, pressmud 40)
A9: D1 | B9: dung_price | C9: 1250 | D9: ₹/t | E9: T2 | F9: NDDB ₹1/kg→spiral; >₹1500 kills viability
A10: D1 | B10: pressmud_price | C10: 550 | D10: ₹/t | E10: T2 | F10: ₹500-600; SEASONAL Oct-Apr
A11: D7 | B11: dung_share | C11: 0.5 | D11: frac | E11: - | F11: co-digestion recipe
A12: D7 | B12: pressmud_share | C12: 0.5 | D12: frac | E12: - | F12: co-digestion recipe
A13: D2 | B13: collectable_dung_kg_per_animal_day | C13: 5 | D13: kg | E13: T2 | F13: dairy-anchored 5; scattered 3
A14: D2 | B14: collection_radius_km_max | C14: 15 | D14: km | E14: T2 | F14: wet-dung economical radius
A15: D4 | B15: cbg_price_rs_per_kg_M1 | C15: 77 | D15: ₹/kg | E15: T2 | F15: SATAT 85% of CNG, NO floor
A16: D4 | B16: cbg_realisation_rs_per_kg_M2 | C16: 90 | D16: ₹/kg | E16: INF | F16: bottled niche realisation
... A40: - | B40: scale_tpd_cbg (LiveModel) | C40: 5 | D40: TPD | E40: - | F40: plant CBG output for LiveModel

Sheet LiveModel
A1: LIVE MODEL — edit Drivers, this recomputes (M1 default). Cross-check vs Python engine at right.
A3: cbg_nameplate_kgday | B3: =Drivers!$C$40*1000
A4: feedstock_tpd | B4: =B3/Drivers!$C$8
A5: blended_feed_₹/t | B5: =Drivers!$C$11*Drivers!$C$9+Drivers!$C$12*Drivers!$C$10
A6: gross_capex ₹ | B6: =B3*Drivers!$C$21*Drivers!$C$23
A7: mnre_subsidy ₹ | B7: =MIN(Drivers!$C$26*(B3/4800),Drivers!$C$27)
A8: dpi_subsidy ₹ | B8: =IF(Drivers!$C$25=1,Drivers!$C$28,0)
A9: subsidy ₹ | B9: =MIN(B7+B8,Drivers!$C$24*B6)
A10: net_capex ₹ | B10: =B6-B9
A11: debt ₹ | B11: =B10*Drivers!$C$33
A12: equity ₹ | B12: =B10*(1-Drivers!$C$33)
A13: depreciation ₹/yr | B13: =B10/Drivers!$C$39
A14: WACC | B14: =Drivers!$C$33*Drivers!$C$34*(1-Drivers!$C$37)+(1-Drivers!$C$33)*Drivers!$C$36
A15: revenue_unit ₹/kg (M1) | B15: =Drivers!$C$15
A18: Year | B18: PLF | C18: CBG kg/yr | D18: Feed t/yr | E18: Feedstock ₹ | F18: Fixed opex ₹ | G18: Var opex ₹ | H18: Logistics ₹ | I18: Revenue ₹ | J18: EBIT ₹ | K18: Reinvest ₹ | L18: Unlev FCF ₹ | M18: Debt bal ₹ | N18: Interest ₹ | O18: Principal ₹ | P18: Equity CF ₹ | Q18: DSCR
A19: 0 | L19: =-B10 | M19: =B11 | P19: =-B12
A20: 1 | B20: =IF(A20=1,Drivers!$C$6,Drivers!$C$5) | C20: =B$3*Drivers!$C$7*B20 | D20: =B$4*Drivers!$C$7*B20 | E20: =D20*B$5 | F20: =Drivers!$C$29*B$6 | G20: =C20*Drivers!$C$30 | H20: =C20*Drivers!$C$31 | I20: =C20*B$15+IF(Drivers!$C$20=1,D20*Drivers!$C$19*Drivers!$C$18,0) | J20: =I20-E20-F20-G20-H20-B$13 | K20: =IF(OR(A20=5,A20=10),Drivers!$C$32*B$6,0) | L20: =J20-IF(J20>0,J20*Drivers!$C$37,0)+B$13-K20 | M20: =B11 | N20: =M20*Drivers!$C$34 | O20: =IF(A20<=Drivers!$C$35,B$11/Drivers!$C$35,0) | P20: =(J20-N20)-IF((J20-N20)>0,(J20-N20)*Drivers!$C$37,0)+B$13-O20-K20 | Q20: =IF((N20+O20)>0,((J20-N20)-IF((J20-N20)>0,(J20-N20)*Drivers!$C$37,0)+B$13+N20)/(N20+O20),"")
A21: 2 | B21: =IF(A21=1,Drivers!$C$6,Drivers!$C$5) | C21: =B$3*Drivers!$C$7*B21 | D21: =B$4*Drivers!$C$7*B21 | E21: =D21*B$5 | F21: =Drivers!$C$29*B$6 | G21: =C21*Drivers!$C$30 | H21: =C21*Drivers!$C$31 | I21: =C21*B$15+IF(Drivers!$C$20=1,D21*Drivers!$C$19*Drivers!$C$18,0) | J21: =I21-E21-F21-G21-H21-B$13 | K21: =IF(OR(A21=5,A21=10),Drivers!$C$32*B$6,0) | L21: =J21-IF(J21>0,J21*Drivers!$C$37,0)+B$13-K21 | M21: =M20-O20 | N21: =M21*Drivers!$C$34 | O21: =IF(A21<=Drivers!$C$35,B$11/Drivers!$C$35,0) | P21: =(J21-N21)-IF((J21-N21)>0,(J21-N21)*Drivers!$C$37,0)+B$13-O21-K21 | Q21: =IF((N21+O21)>0,((J21-N21)-IF((J21-N21)>0,(J21-N21)*Drivers!$C$37,0)+B$13+N21)/(N21+O21),"")
A22: 3 | B22: =IF(A22=1,Drivers!$C$6,Drivers!$C$5) | C22: =B$3*Drivers!$C$7*B22 | D22: =B$4*Drivers!$C$7*B22 | E22: =D22*B$5 | F22: =Drivers!$C$29*B$6 | G22: =C22*Drivers!$C$30 | H22: =C22*Drivers!$C$31 | I22: =C22*B$15+IF(Drivers!$C$20=1,D22*Drivers!$C$19*Drivers!$C$18,0) | J22: =I22-E22-F22-G22-H22-B$13 | K22: =IF(OR(A22=5,A22=10),Drivers!$C$32*B$6,0) | L22: =J22-IF(J22>0,J22*Drivers!$C$37,0)+B$13-K22 | M22: =M21-O21 | N22: =M22*Drivers!$C$34 | O22: =IF(A22<=Drivers!$C$35,B$11/Drivers!$C$35,0) | P22: =(J22-N22)-IF((J22-N22)>0,(J22-N22)*Drivers!$C$37,0)+B$13-O22-K22 | Q22: =IF((N22+O22)>0,((J22-N22)-IF((J22-N22)>0,(J22-N22)*Drivers!$C$37,0)+B$13+N22)/(N22+O22),"")
A23: 4 | B23: =IF(A23=1,Drivers!$C$6,Drivers!$C$5) | C23: =B$3*Drivers!$C$7*B23 | D23: =B$4*Drivers!$C$7*B23 | E23: =D23*B$5 | F23: =Drivers!$C$29*B$6 | G23: =C23*Drivers!$C$30 | H23: =C23*Drivers!$C$31 | I23: =C23*B$15+IF(Drivers!$C$20=1,D23*Drivers!$C$19*Drivers!$C$18,0) | J23: =I23-E23-F23-G23-H23-B$13 | K23: =IF(OR(A23=5,A23=10),Drivers!$C$32*B$6,0) | L23: =J23-IF(J23>0,J23*Drivers!$C$37,0)+B$13-K23 | M23: =M22-O22 | N23: =M23*Drivers!$C$34 | O23: =IF(A23<=Drivers!$C$35,B$11/Drivers!$C$35,0) | P23: =(J23-N23)-IF((J23-N23)>0,(J23-N23)*Drivers!$C$37,0)+B$13-O23-K23 | Q23: =IF((N23+O23)>0,((J23-N23)-IF((J23-N23)>0,(J23-N23)*Drivers!$C$37,0)+B$13+N23)/(N23+O23),"")
A24: 5 | B24: =IF(A24=1,Drivers!$C$6,Drivers!$C$5) | C24: =B$3*Drivers!$C$7*B24 | D24: =B$4*Drivers!$C$7*B24 | E24: =D24*B$5 | F24: =Drivers!$C$29*B$6 | G24: =C24*Drivers!$C$30 | H24: =C24*Drivers!$C$31 | I24: =C24*B$15+IF(Drivers!$C$20=1,D24*Drivers!$C$19*Drivers!$C$18,0) | J24: =I24-E24-F24-G24-H24-B$13 | K24: =IF(OR(A24=5,A24=10),Drivers!$C$32*B$6,0) | L24: =J24-IF(J24>0,J24*Drivers!$C$37,0)+B$13-K24 | M24: =M23-O23 | N24: =M24*Drivers!$C$34 | O24: =IF(A24<=Drivers!$C$35,B$11/Drivers!$C$35,0) | P24: =(J24-N24)-IF((J24-N24)>0,(J24-N24)*Drivers!$C$37,0)+B$13-O24-K24 | Q24: =IF((N24+O24)>0,((J24-N24)-IF((J24-N24)>0,(J24-N24)*Drivers!$C$37,0)+B$13+N24)/(N24+O24),"")
A25: 6 | B25: =IF(A25=1,Drivers!$C$6,Drivers!$C$5) | C25: =B$3*Drivers!$C$7*B25 | D25: =B$4*Drivers!$C$7*B25 | E25: =D25*B$5 | F25: =Drivers!$C$29*B$6 | G25: =C25*Drivers!$C$30 | H25: =C25*Drivers!$C$31 | I25: =C25*B$15+IF(Drivers!$C$20=1,D25*Drivers!$C$19*Drivers!$C$18,0) | J25: =I25-E25-F25-G25-H25-B$13 | K25: =IF(OR(A25=5,A25=10),Drivers!$C$32*B$6,0) | L25: =J25-IF(J25>0,J25*Drivers!$C$37,0)+B$13-K25 | M25: =M24-O24 | N25: =M25*Drivers!$C$34 | O25: =IF(A25<=Drivers!$C$35,B$11/Drivers!$C$35,0) | P25: =(J25-N25)-IF((J25-N25)>0,(J25-N25)*Drivers!$C$37,0)+B$13-O25-K25 | Q25: =IF((N25+O25)>0,((J25-N25)-IF((J25-N25)>0,(J25-N25)*Drivers!$C$37,0)+B$13+N25)/(N25+O25),"")
A26: 7 | B26: =IF(A26=1,Drivers!$C$6,Drivers!$C$5) | C26: =B$3*Drivers!$C$7*B26 | D26: =B$4*Drivers!$C$7*B26 | E26: =D26*B$5 | F26: =Drivers!$C$29*B$6 | G26: =C26*Drivers!$C$30 | H26: =C26*Drivers!$C$31 | I26: =C26*B$15+IF(Drivers!$C$20=1,D26*Drivers!$C$19*Drivers!$C$18,0) | J26: =I26-E26-F26-G26-H26-B$13 | K26: =IF(OR(A26=5,A26=10),Drivers!$C$32*B$6,0) | L26: =J26-IF(J26>0,J26*Drivers!$C$37,0)+B$13-K26 | M26: =M25-O25 | N26: =M26*Drivers!$C$34 | O26: =IF(A26<=Drivers!$C$35,B$11/Drivers!$C$35,0) | P26: =(J26-N26)-IF((J26-N26)>0,(J26-N26)*Drivers!$C$37,0)+B$13-O26-K26 | Q26: =IF((N26+O26)>0,((J26-N26)-IF((J26-N26)>0,(J26-N26)*Drivers!$C$37,0)+B$13+N26)/(N26+O26),"")
A27: 8 | B27: =IF(A27=1,Drivers!$C$6,Drivers!$C$5) | C27: =B$3*Drivers!$C$7*B27 | D27: =B$4*Drivers!$C$7*B27 | E27: =D27*B$5 | F27: =Drivers!$C$29*B$6 | G27: =C27*Drivers!$C$30 | H27: =C27*Drivers!$C$31 | I27: =C27*B$15+IF(Drivers!$C$20=1,D27*Drivers!$C$19*Drivers!$C$18,0) | J27: =I27-E27-F27-G27-H27-B$13 | K27: =IF(OR(A27=5,A27=10),Drivers!$C$32*B$6,0) | L27: =J27-IF(J27>0,J27*Drivers!$C$37,0)+B$13-K27 | M27: =M26-O26 | N27: =M27*Drivers!$C$34 | O27: =IF(A27<=Drivers!$C$35,B$11/Drivers!$C$35,0) | P27: =(J27-N27)-IF((J27-N27)>0,(J27-N27)*Drivers!$C$37,0)+B$13-O27-K27 | Q27: =IF((N27+O27)>0,((J27-N27)-IF((J27-N27)>0,(J27-N27)*Drivers!$C$37,0)+B$13+N27)/(N27+O27),"")
A28: 9 | B28: =IF(A28=1,Drivers!$C$6,Drivers!$C$5) | C28: =B$3*Drivers!$C$7*B28 | D28: =B$4*Drivers!$C$7*B28 | E28: =D28*B$5 | F28: =Drivers!$C$29*B$6 | G28: =C28*Drivers!$C$30 | H28: =C28*Drivers!$C$31 | I28: =C28*B$15+IF(Drivers!$C$20=1,D28*Drivers!$C$19*Drivers!$C$18,0) | J28: =I28-E28-F28-G28-H28-B$13 | K28: =IF(OR(A28=5,A28=10),Drivers!$C$32*B$6,0) | L28: =J28-IF(J28>0,J28*Drivers!$C$37,0)+B$13-K28 | M28: =M27-O27 | N28: =M28*Drivers!$C$34 | O28: =IF(A28<=Drivers!$C$35,B$11/Drivers!$C$35,0) | P28: =(J28-N28)-IF((J28-N28)>0,(J28-N28)*Drivers!$C$37,0)+B$13-O28-K28 | Q28: =IF((N28+O28)>0,((J28-N28)-IF((J28-N28)>0,(J28-N28)*Drivers!$C$37,0)+B$13+N28)/(N28+O28),"")
A29: 10 | B29: =IF(A29=1,Drivers!$C$6,Drivers!$C$5) | C29: =B$3*Drivers!$C$7*B29 | D29: =B$4*Drivers!$C$7*B29 | E29: =D29*B$5 | F29: =Drivers!$C$29*B$6 | G29: =C29*Drivers!$C$30 | H29: =C29*Drivers!$C$31 | I29: =C29*B$15+IF(Drivers!$C$20=1,D29*Drivers!$C$19*Drivers!$C$18,0) | J29: =I29-E29-F29-G29-H29-B$13 | K29: =IF(OR(A29=5,A29=10),Drivers!$C$32*B$6,0) | L29: =J29-IF(J29>0,J29*Drivers!$C$37,0)+B$13-K29 | M29: =M28-O28 | N29: =M29*Drivers!$C$34 | O29: =IF(A29<=Drivers!$C$35,B$11/Drivers!$C$35,0) | P29: =(J29-N29)-IF((J29-N29)>0,(J29-N29)*Drivers!$C$37,0)+B$13-O29-K29 | Q29: =IF((N29+O29)>0,((J29-N29)-IF((J29-N29)>0,(J29-N29)*Drivers!$C$37,0)+B$13+N29)/(N29+O29),"")
A30: 11 | B30: =IF(A30=1,Drivers!$C$6,Drivers!$C$5) | C30: =B$3*Drivers!$C$7*B30 | D30: =B$4*Drivers!$C$7*B30 | E30: =D30*B$5 | F30: =Drivers!$C$29*B$6 | G30: =C30*Drivers!$C$30 | H30: =C30*Drivers!$C$31 | I30: =C30*B$15+IF(Drivers!$C$20=1,D30*Drivers!$C$19*Drivers!$C$18,0) | J30: =I30-E30-F30-G30-H30-B$13 | K30: =IF(OR(A30=5,A30=10),Drivers!$C$32*B$6,0) | L30: =J30-IF(J30>0,J30*Drivers!$C$37,0)+B$13-K30 | M30: =M29-O29 | N30: =M30*Drivers!$C$34 | O30: =IF(A30<=Drivers!$C$35,B$11/Drivers!$C$35,0) | P30: =(J30-N30)-IF((J30-N30)>0,(J30-N30)*Drivers!$C$37,0)+B$13-O30-K30 | Q30: =IF((N30+O30)>0,((J30-N30)-IF((J30-N30)>0,(J30-N30)*Drivers!$C$37,0)+B$13+N30)/(N30+O30),"")
A31: 12 | B31: =IF(A31=1,Drivers!$C$6,Drivers!$C$5) | C31: =B$3*Drivers!$C$7*B31 | D31: =B$4*Drivers!$C$7*B31 | E31: =D31*B$5 | F31: =Drivers!$C$29*B$6 | G31: =C31*Drivers!$C$30 | H31: =C31*Drivers!$C$31 | I31: =C31*B$15+IF(Drivers!$C$20=1,D31*Drivers!$C$19*Drivers!$C$18,0) | J31: =I31-E31-F31-G31-H31-B$13 | K31: =IF(OR(A31=5,A31=10),Drivers!$C$32*B$6,0) | L31: =J31-IF(J31>0,J31*Drivers!$C$37,0)+B$13-K31 | M31: =M30-O30 | N31: =M31*Drivers!$C$34 | O31: =IF(A31<=Drivers!$C$35,B$11/Drivers!$C$35,0) | P31: =(J31-N31)-IF((J31-N31)>0,(J31-N31)*Drivers!$C$37,0)+B$13-O31-K31 | Q31: =IF((N31+O31)>0,((J31-N31)-IF((J31-N31)>0,(J31-N31)*Drivers!$C$37,0)+B$13+N31)/(N31+O31),"")
A32: 13 | B32: =IF(A32=1,Drivers!$C$6,Drivers!$C$5) | C32: =B$3*Drivers!$C$7*B32 | D32: =B$4*Drivers!$C$7*B32 | E32: =D32*B$5 | F32: =Drivers!$C$29*B$6 | G32: =C32*Drivers!$C$30 | H32: =C32*Drivers!$C$31 | I32: =C32*B$15+IF(Drivers!$C$20=1,D32*Drivers!$C$19*Drivers!$C$18,0) | J32: =I32-E32-F32-G32-H32-B$13 | K32: =IF(OR(A32=5,A32=10),Drivers!$C$32*B$6,0) | L32: =J32-IF(J32>0,J32*Drivers!$C$37,0)+B$13-K32 | M32: =M31-O31 | N32: =M32*Drivers!$C$34 | O32: =IF(A32<=Drivers!$C$35,B$11/Drivers!$C$35,0) | P32: =(J32-N32)-IF((J32-N32)>0,(J32-N32)*Drivers!$C$37,0)+B$13-O32-K32 | Q32: =IF((N32+O32)>0,((J32-N32)-IF((J32-N32)>0,(J32-N32)*Drivers!$C$37,0)+B$13+N32)/(N32+O32),"")
... A34: 15 | B34: =IF(A34=1,Drivers!$C$6,Drivers!$C$5) | C34: =B$3*Drivers!$C$7*B34 | D34: =B$4*Drivers!$C$7*B34 | E34: =D34*B$5 | F34: =Drivers!$C$29*B$6 | G34: =C34*Drivers!$C$30 | H34: =C34*Drivers!$C$31 | I34: =C34*B$15+IF(Drivers!$C$20=1,D34*Drivers!$C$19*Drivers!$C$18,0) | J34: =I34-E34-F34-G34-H34-B$13 | K34: =IF(OR(A34=5,A34=10),Drivers!$C$32*B$6,0) | L34: =J34-IF(J34>0,J34*Drivers!$C$37,0)+B$13-K34 | M34: =M33-O33 | N34: =M34*Drivers!$C$34 | O34: =IF(A34<=Drivers!$C$35,B$11/Drivers!$C$35,0) | P34: =(J34-N34)-IF((J34-N34)>0,(J34-N34)*Drivers!$C$37,0)+B$13-O34-K34 | Q34: =IF((N34+O34)>0,((J34-N34)-IF((J34-N34)>0,(J34-N34)*Drivers!$C$37,0)+B$13+N34)/(N34+O34),"")
A36: RESULTS | D36: (should match column B at base drivers)
A37: Project IRR | B37: =IRR(L19:L34) | D37: Python engine → | E37: 0.1009
A38: Equity IRR | B38: =IRR(P19:P34) | E38: 0.1256
A39: NPV @ WACC ₹ | B39: =L19+NPV(B14,L20:L34) | E39: -3284854
A40: Min DSCR | B40: =MIN(Q20:Q34) | E40: 0.86

Sheet Scenarios
A1: SCENARIOS — M1 injection @ 5 TPD (Python engine snapshot)
A3: Scenario | B3: Project IRR | C3: Equity IRR | D3: NPV @WACC ₹cr | E3: Min DSCR | F3: Payback (yr)
A4: Tailwind | B4: 0.30050094 | C4: 0.66591394 | D4: 22.02 | E4: 1.32 | F4: 4
A5: Base | B5: 0.10093235 | C5: 0.12560015 | D5: -0.33 | E5: 0.86 | F5: 8
A6: Stress | B6: -0.15807499 | C6: -0.33754612 | D6: -17.76 | E6: 0.06 | F6: >15
A8: Tailwind = PLF .70 + DPI subsidy + FOM clears @₹1500 + CBG ₹85 + dung eased. Base = PLF .50, no DPI, FOM ₹1250, CBG ₹77, dung ₹1250. Stress = PLF .45, feedstock +40%, FOM=0, CBG ₹70 (OMC gaps).

Sheet Sensitivity
A1: SENSITIVITY — tornado, Monte-Carlo, frontier (Python engine)
A3: TORNADO (equity IRR, M1@5TPD) | B3: low | C3: high | D3: swing (pts)
A4: PLF 0.35-0.70 | B4: -0.035369883 | C4: 0.32193948 | D4: 35.7
A5: Dung/feed price (+/-40%) | B5: 0.27401043 | C5: -0.011289474 | D5: 28.5
A6: CBG price ₹65-90/kg | B6: -0.00019685931 | C6: 0.27295654 | D6: 27.3
A7: Capex ₹40k-55k/kgday | B7: 0.21443962 | C7: 0.013074648 | D7: 20.1
A8: FOM ₹0-1500/t | B8: -0.016835058 | C8: 0.15595324 | D8: 17.3
A9: Subsidy 20-35% / DPI | B9: 0.12560015 | C9: 0.21880715 | D9: 9.3
A10: Cost of debt 9-13% | B10: 0.14165842 | C10: 0.10163739 | D10: 4
A12: Base equity IRR = 12.6%
A14: MONTE-CARLO (5,000 draws, equity IRR)
A15: P10 | B15: -0.1582
A16: P50 | B16: -0.0033
A17: P90 | B17: 0.1727
A18: P(IRR>WACC) | B18: 0.2086
A19: P(IRR>20%) | B19: 0.0692
A20: P(IRR<0) | B20: 0.5092
A22: FRONTIER project IRR — best/worst corner
A23: dung ₹800 / CBG ₹95 | B23: 0.2112
A24: dung ₹2600 / CBG ₹55 | B24: -0.5
